hyperdex/__init__.py
hyperdex/cli.py
tools/__init__.py
tools/gh_repo_fetch_forks_shane.py
tools/gh_repo_fetch_index_cello.py
tools/gh_repo_fetch_index_shane.py
tools/gh_repo_release_initial_cello.py
tools/gh_repo_release_initial_shane.py
tools/gh_repo_release_latest_cello.py
tools/gh_repo_release_latest_shane.py
tools/gh_repo_setup_secret.py
tools/gh_repo_update_readmes.py
tools/utils.py
hyperdex-0.1.1.dist-info/METADATA
hyperdex-0.1.1.dist-info/WHEEL
hyperdex-0.1.1.dist-info/entry_points.txt
hyperdex-0.1.1.dist-info/RECORD
