Metadata-Version: 2.4
Name: hyperdex
Version: 0.1.1
Summary: GitHub Repository Catalog: Fetching, indexing, and organizing READMEs.
Project-URL: Homepage, https://github.com/shaneholloman/hyperdex
Author-email: Shane Holloman <shaneholloman@gmail.com>
License: MIT
Classifier: Development Status :: 3 - Alpha
Classifier: Intended Audience :: Developers
Classifier: License :: OSI Approved :: MIT License
Classifier: Programming Language :: Python :: 3
Classifier: Programming Language :: Python :: 3.10
Classifier: Programming Language :: Python :: 3.11
Requires-Python: >=3.10
Requires-Dist: packaging
